{
    "head": {
        "vars": [
            "item",
            "itemLabel",
            "itemDescription",
            "article"
        ]
    },
    "results": {
        "bindings": [
            {
                "item": {
                    "type": "uri",
                    "value": "http:\/\/www.wikidata.org\/entity\/Q43900758"
                },
                "article": {
                    "type": "uri",
                    "value": "https:\/\/en.wikipedia.org\/wiki\/Christopher_Snow"
                },
                "itemLabel": {
                    "xml:lang": "en",
                    "type": "literal",
                    "value": "Christopher Snow"
                },
                "itemDescription": {
                    "xml:lang": "en",
                    "type": "literal",
                    "value": "Royal Navy admiral"
                }
            },
            {
                "item": {
                    "type": "uri",
                    "value": "http:\/\/www.wikidata.org\/entity\/Q43901011"
                },
                "article": {
                    "type": "uri",
                    "value": "https:\/\/en.wikipedia.org\/wiki\/Azazet_Habtezghi_Kidane"
                },
                "itemLabel": {
                    "xml:lang": "en",
                    "type": "literal",
                    "value": "Azazet Habtezghi Kidane"
                },
                "itemDescription": {
                    "xml:lang": "en",
                    "type": "literal",
                    "value": "Eritrean-born British nun and human trafficking activist"
                }
            },
            {
                "item": {
                    "type": "uri",
                    "value": "http:\/\/www.wikidata.org\/entity\/Q43901019"
                },
                "article": {
                    "type": "uri",
                    "value": "https:\/\/en.wikipedia.org\/wiki\/Jamie_Shelton"
                },
                "itemLabel": {
                    "xml:lang": "en",
                    "type": "literal",
                    "value": "Jamie Shelton"
                },
                "itemDescription": {
                    "xml:lang": "en",
                    "type": "literal",
                    "value": "British actor"
                }
            },
            {
                "item": {
                    "type": "uri",
                    "value": "http:\/\/www.wikidata.org\/entity\/Q43901096"
                },
                "article": {
                    "type": "uri",
                    "value": "https:\/\/en.wikipedia.org\/wiki\/Niall_Macdonald"
                },
                "itemLabel": {
                    "xml:lang": "en",
                    "type": "literal",
                    "value": "Niall Macdonald"
                },
                "itemDescription": {
                    "xml:lang": "en",
                    "type": "literal",
                    "value": "Scottish visual artist"
                }
            },
            {
                "item": {
                    "type": "uri",
                    "value": "http:\/\/www.wikidata.org\/entity\/Q43901104"
                },
                "article": {
                    "type": "uri",
                    "value": "https:\/\/en.wikipedia.org\/wiki\/Lizzie_Farey"
                },
                "itemLabel": {
                    "xml:lang": "en",
                    "type": "literal",
                    "value": "Lizzie Farey"
                },
                "itemDescription": {
                    "xml:lang": "en",
                    "type": "literal",
                    "value": "Scottish artist"
                }
            },
            {
                "item": {
                    "type": "uri",
                    "value": "http:\/\/www.wikidata.org\/entity\/Q43901257"
                },
                "article": {
                    "type": "uri",
                    "value": "https:\/\/en.wikipedia.org\/wiki\/Rosemary_Joy_Hendry"
                },
                "itemLabel": {
                    "xml:lang": "en",
                    "type": "literal",
                    "value": "Rosemary Joy Hendry"
                },
                "itemDescription": {
                    "xml:lang": "en",
                    "type": "literal",
                    "value": "British anthropologist (1945-)"
                }
            },
            {
                "item": {
                    "type": "uri",
                    "value": "http:\/\/www.wikidata.org\/entity\/Q43901361"
                },
                "article": {
                    "type": "uri",
                    "value": "https:\/\/en.wikipedia.org\/wiki\/Francis_McGlone"
                },
                "itemLabel": {
                    "xml:lang": "en",
                    "type": "literal",
                    "value": "Francis McGlone"
                }
            },
            {
                "item": {
                    "type": "uri",
                    "value": "http:\/\/www.wikidata.org\/entity\/Q43948042"
                },
                "article": {
                    "type": "uri",
                    "value": "https:\/\/en.wikipedia.org\/wiki\/Christine_Orr"
                },
                "itemLabel": {
                    "xml:lang": "en",
                    "type": "literal",
                    "value": "Christine Orr"
                },
                "itemDescription": {
                    "xml:lang": "en",
                    "type": "literal",
                    "value": "Scottish novelist, playwright, poet, actor, theatre director and broadcaster (1899-1963)"
                }
            },
            {
                "item": {
                    "type": "uri",
                    "value": "http:\/\/www.wikidata.org\/entity\/Q43954575"
                },
                "article": {
                    "type": "uri",
                    "value": "https:\/\/en.wikipedia.org\/wiki\/Sheila_Begbie"
                },
                "itemLabel": {
                    "xml:lang": "en",
                    "type": "literal",
                    "value": "Sheila Begbie"
                },
                "itemDescription": {
                    "xml:lang": "en",
                    "type": "literal",
                    "value": "Scottish association football player"
                }
            },
            {
                "item": {
                    "type": "uri",
                    "value": "http:\/\/www.wikidata.org\/entity\/Q43956385"
                },
                "article": {
                    "type": "uri",
                    "value": "https:\/\/en.wikipedia.org\/wiki\/Vera_Evison"
                },
                "itemLabel": {
                    "xml:lang": "en",
                    "type": "literal",
                    "value": "Vera I. Evison"
                },
                "itemDescription": {
                    "xml:lang": "en",
                    "type": "literal",
                    "value": "British archaeologist"
                }
            },
            {
                "item": {
                    "type": "uri",
                    "value": "http:\/\/www.wikidata.org\/entity\/Q43956558"
                },
                "itemLabel": {
                    "xml:lang": "en",
                    "type": "literal",
                    "value": "Stephen A. Stansfeld"
                },
                "itemDescription": {
                    "xml:lang": "en",
                    "type": "literal",
                    "value": "British researcher"
                }
            },
            {
                "item": {
                    "type": "uri",
                    "value": "http:\/\/www.wikidata.org\/entity\/Q43963786"
                },
                "itemLabel": {
                    "xml:lang": "en",
                    "type": "literal",
                    "value": "A. W. G. Lowther"
                },
                "itemDescription": {
                    "xml:lang": "en",
                    "type": "literal",
                    "value": "British architect and archaeologist; FSA, died 1973"
                }
            },
            {
                "item": {
                    "type": "uri",
                    "value": "http:\/\/www.wikidata.org\/entity\/Q43969205"
                },
                "article": {
                    "type": "uri",
                    "value": "https:\/\/en.wikipedia.org\/wiki\/Clare_Wheatley"
                },
                "itemLabel": {
                    "xml:lang": "en",
                    "type": "literal",
                    "value": "Clare Wheatley"
                },
                "itemDescription": {
                    "xml:lang": "en",
                    "type": "literal",
                    "value": "English association football player and administrator (born 1971)"
                }
            },
            {
                "item": {
                    "type": "uri",
                    "value": "http:\/\/www.wikidata.org\/entity\/Q43971190"
                },
                "itemLabel": {
                    "xml:lang": "en",
                    "type": "literal",
                    "value": "Jean M. Cook"
                },
                "itemDescription": {
                    "xml:lang": "en",
                    "type": "literal",
                    "value": "archaeologist, curator, and teacher (1927-2001)"
                }
            },
            {
                "item": {
                    "type": "uri",
                    "value": "http:\/\/www.wikidata.org\/entity\/Q43993927"
                },
                "article": {
                    "type": "uri",
                    "value": "https:\/\/en.wikipedia.org\/wiki\/Emma_Thynn,_Marchioness_of_Bath"
                },
                "itemLabel": {
                    "xml:lang": "en",
                    "type": "literal",
                    "value": "Emma Thynn, Marchioness of Bath"
                },
                "itemDescription": {
                    "xml:lang": "en",
                    "type": "literal",
                    "value": "English model, chef, and aristocrat"
                }
            },
            {
                "item": {
                    "type": "uri",
                    "value": "http:\/\/www.wikidata.org\/entity\/Q43997477"
                },
                "article": {
                    "type": "uri",
                    "value": "https:\/\/en.wikipedia.org\/wiki\/Ronald_West"
                },
                "itemLabel": {
                    "xml:lang": "en",
                    "type": "literal",
                    "value": "Ronald West"
                },
                "itemDescription": {
                    "xml:lang": "en",
                    "type": "literal",
                    "value": "British racewalker"
                }
            },
            {
                "item": {
                    "type": "uri",
                    "value": "http:\/\/www.wikidata.org\/entity\/Q44000472"
                },
                "itemLabel": {
                    "xml:lang": "en",
                    "type": "literal",
                    "value": "William Hutton Marwick"
                },
                "itemDescription": {
                    "xml:lang": "en",
                    "type": "literal",
                    "value": "Scottish presbyterian missionary at Old Calabar (1863-1940)"
                }
            },
            {
                "item": {
                    "type": "uri",
                    "value": "http:\/\/www.wikidata.org\/entity\/Q44034764"
                },
                "itemLabel": {
                    "xml:lang": "en",
                    "type": "literal",
                    "value": "Dick Denney"
                },
                "itemDescription": {
                    "xml:lang": "en",
                    "type": "literal",
                    "value": "British designer of guitar amplifiers"
                }
            },
            {
                "item": {
                    "type": "uri",
                    "value": "http:\/\/www.wikidata.org\/entity\/Q44040232"
                },
                "article": {
                    "type": "uri",
                    "value": "https:\/\/en.wikipedia.org\/wiki\/Alexander_Murray,_9th_Earl_of_Mansfield"
                },
                "itemLabel": {
                    "xml:lang": "en",
                    "type": "literal",
                    "value": "Alexander Murray, 9th Earl of Mansfield"
                },
                "itemDescription": {
                    "xml:lang": "en",
                    "type": "literal",
                    "value": "Scottish nobleman (born 1956)"
                }
            },
            {
                "item": {
                    "type": "uri",
                    "value": "http:\/\/www.wikidata.org\/entity\/Q44043530"
                },
                "article": {
                    "type": "uri",
                    "value": "https:\/\/en.wikipedia.org\/wiki\/Karen_Faulds"
                },
                "itemLabel": {
                    "xml:lang": "en",
                    "type": "literal",
                    "value": "Karen Faulds"
                },
                "itemDescription": {
                    "xml:lang": "en",
                    "type": "literal",
                    "value": "Analytical chemist"
                }
            },
            {
                "item": {
                    "type": "uri",
                    "value": "http:\/\/www.wikidata.org\/entity\/Q44044407"
                },
                "article": {
                    "type": "uri",
                    "value": "https:\/\/en.wikipedia.org\/wiki\/John_Mattock_(rose_grower)"
                },
                "itemLabel": {
                    "xml:lang": "en",
                    "type": "literal",
                    "value": "John Mattock"
                },
                "itemDescription": {
                    "xml:lang": "en",
                    "type": "literal",
                    "value": "rose grower"
                }
            },
            {
                "item": {
                    "type": "uri",
                    "value": "http:\/\/www.wikidata.org\/entity\/Q44047366"
                },
                "article": {
                    "type": "uri",
                    "value": "https:\/\/en.wikipedia.org\/wiki\/Mitchell_Rao"
                },
                "itemLabel": {
                    "xml:lang": "en",
                    "type": "literal",
                    "value": "Mitchell Rao"
                },
                "itemDescription": {
                    "xml:lang": "en",
                    "type": "literal",
                    "value": "cricketer (born 1997)"
                }
            },
            {
                "item": {
                    "type": "uri",
                    "value": "http:\/\/www.wikidata.org\/entity\/Q44056211"
                },
                "article": {
                    "type": "uri",
                    "value": "https:\/\/en.wikipedia.org\/wiki\/Irena_Bauman"
                },
                "itemLabel": {
                    "xml:lang": "en",
                    "type": "literal",
                    "value": "Irena Bauman"
                },
                "itemDescription": {
                    "xml:lang": "en",
                    "type": "literal",
                    "value": "British architect"
                }
            },
            {
                "item": {
                    "type": "uri",
                    "value": "http:\/\/www.wikidata.org\/entity\/Q44059945"
                },
                "itemLabel": {
                    "xml:lang": "en",
                    "type": "literal",
                    "value": "Mr. Shepherd"
                },
                "itemDescription": {
                    "xml:lang": "en",
                    "type": "literal",
                    "value": "English association football manager"
                }
            },
            {
                "item": {
                    "type": "uri",
                    "value": "http:\/\/www.wikidata.org\/entity\/Q44070372"
                },
                "article": {
                    "type": "uri",
                    "value": "https:\/\/en.wikipedia.org\/wiki\/Morgan_Williams_(rugby_union,_born_1995)"
                },
                "itemLabel": {
                    "xml:lang": "en",
                    "type": "literal",
                    "value": "Morgan Williams"
                },
                "itemDescription": {
                    "xml:lang": "en",
                    "type": "literal",
                    "value": "Welsh rugby union player"
                }
            },
            {
                "item": {
                    "type": "uri",
                    "value": "http:\/\/www.wikidata.org\/entity\/Q44070759"
                },
                "article": {
                    "type": "uri",
                    "value": "https:\/\/en.wikipedia.org\/wiki\/Tessa_Lynch"
                },
                "itemLabel": {
                    "xml:lang": "en",
                    "type": "literal",
                    "value": "Tessa Lynch"
                },
                "itemDescription": {
                    "xml:lang": "en",
                    "type": "literal",
                    "value": "British painter"
                }
            },
            {
                "item": {
                    "type": "uri",
                    "value": "http:\/\/www.wikidata.org\/entity\/Q44071098"
                },
                "article": {
                    "type": "uri",
                    "value": "https:\/\/en.wikipedia.org\/wiki\/Alex_Clark_(squash_player)"
                },
                "itemLabel": {
                    "xml:lang": "en",
                    "type": "literal",
                    "value": "Alex Clark"
                },
                "itemDescription": {
                    "xml:lang": "en",
                    "type": "literal",
                    "value": "Scottish squash player"
                }
            },
            {
                "item": {
                    "type": "uri",
                    "value": "http:\/\/www.wikidata.org\/entity\/Q44083605"
                },
                "itemLabel": {
                    "xml:lang": "en",
                    "type": "literal",
                    "value": "T. S. Church"
                },
                "itemDescription": {
                    "xml:lang": "en",
                    "type": "literal",
                    "value": "British fantasy author"
                }
            },
            {
                "item": {
                    "type": "uri",
                    "value": "http:\/\/www.wikidata.org\/entity\/Q44094675"
                },
                "article": {
                    "type": "uri",
                    "value": "https:\/\/en.wikipedia.org\/wiki\/Fraer_Morrow"
                },
                "itemLabel": {
                    "xml:lang": "en",
                    "type": "literal",
                    "value": "Fraer Morrow"
                },
                "itemDescription": {
                    "xml:lang": "en",
                    "type": "literal",
                    "value": "English weightlifter"
                }
            },
            {
                "item": {
                    "type": "uri",
                    "value": "http:\/\/www.wikidata.org\/entity\/Q44096871"
                },
                "article": {
                    "type": "uri",
                    "value": "https:\/\/en.wikipedia.org\/wiki\/Agnes_Mary_Field"
                },
                "itemLabel": {
                    "xml:lang": "en",
                    "type": "literal",
                    "value": "Agnes Mary Field"
                },
                "itemDescription": {
                    "xml:lang": "en",
                    "type": "literal",
                    "value": "British film producer and director (1896-1968)"
                }
            },
            {
                "item": {
                    "type": "uri",
                    "value": "http:\/\/www.wikidata.org\/entity\/Q44097104"
                },
                "itemLabel": {
                    "xml:lang": "en",
                    "type": "literal",
                    "value": "Peggy E. Titterton"
                },
                "itemDescription": {
                    "xml:lang": "en",
                    "type": "literal",
                    "value": "laboratory assistant at the University of Birmingham and then on the Manhattan Project at Los Alamos"
                }
            },
            {
                "item": {
                    "type": "uri",
                    "value": "http:\/\/www.wikidata.org\/entity\/Q44101058"
                },
                "article": {
                    "type": "uri",
                    "value": "https:\/\/en.wikipedia.org\/wiki\/Catherine_Manning"
                },
                "itemLabel": {
                    "xml:lang": "en",
                    "type": "literal",
                    "value": "Catherine Manning"
                },
                "itemDescription": {
                    "xml:lang": "en",
                    "type": "literal",
                    "value": "British novelist"
                }
            },
            {
                "item": {
                    "type": "uri",
                    "value": "http:\/\/www.wikidata.org\/entity\/Q44101853"
                },
                "article": {
                    "type": "uri",
                    "value": "https:\/\/en.wikipedia.org\/wiki\/John_Edgington"
                },
                "itemLabel": {
                    "xml:lang": "en",
                    "type": "literal",
                    "value": "John Edgington"
                },
                "itemDescription": {
                    "xml:lang": "en",
                    "type": "literal",
                    "value": "British racewalker"
                }
            },
            {
                "item": {
                    "type": "uri",
                    "value": "http:\/\/www.wikidata.org\/entity\/Q44118178"
                },
                "itemLabel": {
                    "xml:lang": "en",
                    "type": "literal",
                    "value": "Michael Shaw"
                },
                "itemDescription": {
                    "xml:lang": "en",
                    "type": "literal",
                    "value": "UK researcher"
                }
            },
            {
                "item": {
                    "type": "uri",
                    "value": "http:\/\/www.wikidata.org\/entity\/Q44123151"
                },
                "itemLabel": {
                    "xml:lang": "en",
                    "type": "literal",
                    "value": "John Bury"
                },
                "itemDescription": {
                    "xml:lang": "en",
                    "type": "literal",
                    "value": "British art historian (1917-2017)"
                }
            },
            {
                "item": {
                    "type": "uri",
                    "value": "http:\/\/www.wikidata.org\/entity\/Q44147168"
                },
                "article": {
                    "type": "uri",
                    "value": "https:\/\/en.wikipedia.org\/wiki\/Belinda_Kirk"
                },
                "itemLabel": {
                    "xml:lang": "en",
                    "type": "literal",
                    "value": "Belinda Kirk"
                },
                "itemDescription": {
                    "xml:lang": "en",
                    "type": "literal",
                    "value": "British explorer"
                }
            },
            {
                "item": {
                    "type": "uri",
                    "value": "http:\/\/www.wikidata.org\/entity\/Q44147210"
                },
                "article": {
                    "type": "uri",
                    "value": "https:\/\/en.wikipedia.org\/wiki\/Melinda_Tan"
                },
                "itemLabel": {
                    "xml:lang": "en",
                    "type": "literal",
                    "value": "Melinda Tan"
                },
                "itemDescription": {
                    "xml:lang": "en",
                    "type": "literal",
                    "value": "British academic"
                }
            },
            {
                "item": {
                    "type": "uri",
                    "value": "http:\/\/www.wikidata.org\/entity\/Q44155502"
                },
                "article": {
                    "type": "uri",
                    "value": "https:\/\/en.wikipedia.org\/wiki\/John_Roberts_(Royal_Navy_officer)"
                },
                "itemLabel": {
                    "xml:lang": "en",
                    "type": "literal",
                    "value": "John Oliver Roberts"
                },
                "itemDescription": {
                    "xml:lang": "en",
                    "type": "literal",
                    "value": "British naval officer"
                }
            },
            {
                "item": {
                    "type": "uri",
                    "value": "http:\/\/www.wikidata.org\/entity\/Q44156509"
                },
                "article": {
                    "type": "uri",
                    "value": "https:\/\/en.wikipedia.org\/wiki\/Philip_Sharp_(Royal_Navy_officer)"
                },
                "itemLabel": {
                    "xml:lang": "en",
                    "type": "literal",
                    "value": "Philip Graham Sharp"
                },
                "itemDescription": {
                    "xml:lang": "en",
                    "type": "literal",
                    "value": "(1913-1988),  British Rear-Admiral"
                }
            },
            {
                "item": {
                    "type": "uri",
                    "value": "http:\/\/www.wikidata.org\/entity\/Q44173507"
                },
                "article": {
                    "type": "uri",
                    "value": "https:\/\/en.wikipedia.org\/wiki\/Anne_M._McKim"
                },
                "itemLabel": {
                    "xml:lang": "en",
                    "type": "literal",
                    "value": "Anne M. McKim"
                },
                "itemDescription": {
                    "xml:lang": "en",
                    "type": "literal",
                    "value": "Scottish-New Zealand academic"
                }
            },
            {
                "item": {
                    "type": "uri",
                    "value": "http:\/\/www.wikidata.org\/entity\/Q44181253"
                },
                "itemLabel": {
                    "xml:lang": "en",
                    "type": "literal",
                    "value": "William Fazan"
                },
                "itemDescription": {
                    "xml:lang": "en",
                    "type": "literal",
                    "value": "British film actor"
                }
            },
            {
                "item": {
                    "type": "uri",
                    "value": "http:\/\/www.wikidata.org\/entity\/Q44187342"
                },
                "article": {
                    "type": "uri",
                    "value": "https:\/\/en.wikipedia.org\/wiki\/Sabbie_Heesh"
                },
                "itemLabel": {
                    "xml:lang": "en",
                    "type": "literal",
                    "value": "Sabbie Heesh"
                },
                "itemDescription": {
                    "xml:lang": "en",
                    "type": "literal",
                    "value": "British field hockey player (1991-)"
                }
            },
            {
                "item": {
                    "type": "uri",
                    "value": "http:\/\/www.wikidata.org\/entity\/Q44189473"
                },
                "article": {
                    "type": "uri",
                    "value": "https:\/\/en.wikipedia.org\/wiki\/Kathryn_Lane"
                },
                "itemLabel": {
                    "xml:lang": "en",
                    "type": "literal",
                    "value": "Kathryn Lane"
                },
                "itemDescription": {
                    "xml:lang": "en",
                    "type": "literal",
                    "value": "English field hockey player"
                }
            },
            {
                "item": {
                    "type": "uri",
                    "value": "http:\/\/www.wikidata.org\/entity\/Q44205475"
                },
                "article": {
                    "type": "uri",
                    "value": "https:\/\/en.wikipedia.org\/wiki\/Ruth_Kempson"
                },
                "itemLabel": {
                    "xml:lang": "en",
                    "type": "literal",
                    "value": "Ruth Kempson"
                },
                "itemDescription": {
                    "xml:lang": "en",
                    "type": "literal",
                    "value": "British linguist"
                }
            },
            {
                "item": {
                    "type": "uri",
                    "value": "http:\/\/www.wikidata.org\/entity\/Q44209242"
                },
                "article": {
                    "type": "uri",
                    "value": "https:\/\/en.wikipedia.org\/wiki\/Gaby_Wood"
                },
                "itemLabel": {
                    "xml:lang": "en",
                    "type": "literal",
                    "value": "Gaby Wood"
                },
                "itemDescription": {
                    "xml:lang": "en",
                    "type": "literal",
                    "value": "British journalist"
                }
            },
            {
                "item": {
                    "type": "uri",
                    "value": "http:\/\/www.wikidata.org\/entity\/Q44246324"
                },
                "article": {
                    "type": "uri",
                    "value": "https:\/\/en.wikipedia.org\/wiki\/Robin_Murray_(economist)"
                },
                "itemLabel": {
                    "xml:lang": "en",
                    "type": "literal",
                    "value": "Robin Murray"
                },
                "itemDescription": {
                    "xml:lang": "en",
                    "type": "literal",
                    "value": "English economist, 1940-2017"
                }
            },
            {
                "item": {
                    "type": "uri",
                    "value": "http:\/\/www.wikidata.org\/entity\/Q44270625"
                },
                "itemLabel": {
                    "xml:lang": "en",
                    "type": "literal",
                    "value": "Mark Wilson"
                },
                "itemDescription": {
                    "xml:lang": "en",
                    "type": "literal",
                    "value": "psychologist"
                }
            },
            {
                "item": {
                    "type": "uri",
                    "value": "http:\/\/www.wikidata.org\/entity\/Q44284493"
                },
                "itemLabel": {
                    "xml:lang": "en",
                    "type": "literal",
                    "value": "Wally Scott"
                },
                "itemDescription": {
                    "xml:lang": "en",
                    "type": "literal",
                    "value": "British musician"
                }
            },
            {
                "item": {
                    "type": "uri",
                    "value": "http:\/\/www.wikidata.org\/entity\/Q44284833"
                },
                "itemLabel": {
                    "xml:lang": "en",
                    "type": "literal",
                    "value": "Ron Hanson"
                },
                "itemDescription": {
                    "xml:lang": "en",
                    "type": "literal",
                    "value": "British musician"
                }
            },
            {
                "item": {
                    "type": "uri",
                    "value": "http:\/\/www.wikidata.org\/entity\/Q44288603"
                },
                "itemLabel": {
                    "xml:lang": "en",
                    "type": "literal",
                    "value": "Tom Jordan"
                },
                "itemDescription": {
                    "xml:lang": "en",
                    "type": "literal",
                    "value": "British musician"
                }
            },
            {
                "item": {
                    "type": "uri",
                    "value": "http:\/\/www.wikidata.org\/entity\/Q44289484"
                },
                "itemLabel": {
                    "xml:lang": "en",
                    "type": "literal",
                    "value": "Roger Marsh"
                },
                "itemDescription": {
                    "xml:lang": "en",
                    "type": "literal",
                    "value": "British musician"
                }
            },
            {
                "item": {
                    "type": "uri",
                    "value": "http:\/\/www.wikidata.org\/entity\/Q44289890"
                },
                "itemLabel": {
                    "xml:lang": "en",
                    "type": "literal",
                    "value": "Bernie Martin"
                },
                "itemDescription": {
                    "xml:lang": "en",
                    "type": "literal",
                    "value": "British musician"
                }
            },
            {
                "item": {
                    "type": "uri",
                    "value": "http:\/\/www.wikidata.org\/entity\/Q44301393"
                },
                "article": {
                    "type": "uri",
                    "value": "https:\/\/en.wikipedia.org\/wiki\/Louis_Stewart_Gumley"
                },
                "itemLabel": {
                    "xml:lang": "en",
                    "type": "literal",
                    "value": "Louis Stewart Gumley"
                }
            },
            {
                "item": {
                    "type": "uri",
                    "value": "http:\/\/www.wikidata.org\/entity\/Q44304217"
                },
                "article": {
                    "type": "uri",
                    "value": "https:\/\/en.wikipedia.org\/wiki\/Jeffrey_Lawton"
                },
                "itemLabel": {
                    "xml:lang": "en",
                    "type": "literal",
                    "value": "Jeffrey Lawton"
                },
                "itemDescription": {
                    "xml:lang": "en",
                    "type": "literal",
                    "value": "British opera singer"
                }
            },
            {
                "item": {
                    "type": "uri",
                    "value": "http:\/\/www.wikidata.org\/entity\/Q44304487"
                },
                "itemLabel": {
                    "xml:lang": "en",
                    "type": "literal",
                    "value": "Stephen Murray"
                },
                "itemDescription": {
                    "xml:lang": "en",
                    "type": "literal",
                    "value": "English barrister"
                }
            },
            {
                "item": {
                    "type": "uri",
                    "value": "http:\/\/www.wikidata.org\/entity\/Q44312928"
                },
                "itemLabel": {
                    "xml:lang": "en",
                    "type": "literal",
                    "value": "Geoffrey Stell"
                },
                "itemDescription": {
                    "xml:lang": "en",
                    "type": "literal",
                    "value": "historian and archaeologist"
                }
            },
            {
                "item": {
                    "type": "uri",
                    "value": "http:\/\/www.wikidata.org\/entity\/Q44314420"
                },
                "article": {
                    "type": "uri",
                    "value": "https:\/\/en.wikipedia.org\/wiki\/Malcolm_Airs"
                },
                "itemLabel": {
                    "xml:lang": "en",
                    "type": "literal",
                    "value": "Malcolm Airs"
                },
                "itemDescription": {
                    "xml:lang": "en",
                    "type": "literal",
                    "value": "architectural historian"
                }
            },
            {
                "item": {
                    "type": "uri",
                    "value": "http:\/\/www.wikidata.org\/entity\/Q44321481"
                },
                "article": {
                    "type": "uri",
                    "value": "https:\/\/en.wikipedia.org\/wiki\/Harriet_Wistrich"
                },
                "itemLabel": {
                    "xml:lang": "en",
                    "type": "literal",
                    "value": "Harriet Wistrich"
                },
                "itemDescription": {
                    "xml:lang": "en",
                    "type": "literal",
                    "value": "British lawyer"
                }
            },
            {
                "item": {
                    "type": "uri",
                    "value": "http:\/\/www.wikidata.org\/entity\/Q44323615"
                },
                "article": {
                    "type": "uri",
                    "value": "https:\/\/en.wikipedia.org\/wiki\/David_M._Palliser"
                },
                "itemLabel": {
                    "xml:lang": "en",
                    "type": "literal",
                    "value": "David M. Palliser"
                },
                "itemDescription": {
                    "xml:lang": "en",
                    "type": "literal",
                    "value": "British historian"
                }
            },
            {
                "item": {
                    "type": "uri",
                    "value": "http:\/\/www.wikidata.org\/entity\/Q44358657"
                },
                "itemLabel": {
                    "xml:lang": "en",
                    "type": "literal",
                    "value": "Kenneth Noel Grant Macleay"
                },
                "itemDescription": {
                    "xml:lang": "en",
                    "type": "literal",
                    "value": "British botanist in Africa, fern specialist (1903-1989)"
                }
            },
            {
                "item": {
                    "type": "uri",
                    "value": "http:\/\/www.wikidata.org\/entity\/Q44375938"
                },
                "itemLabel": {
                    "xml:lang": "en",
                    "type": "literal",
                    "value": "Hugo John Robertson Slim"
                },
                "itemDescription": {
                    "xml:lang": "en",
                    "type": "literal",
                    "value": "M, #578937, b. 28 August 1961"
                }
            },
            {
                "item": {
                    "type": "uri",
                    "value": "http:\/\/www.wikidata.org\/entity\/Q44376416"
                },
                "itemLabel": {
                    "xml:lang": "en",
                    "type": "literal",
                    "value": "Rob Ivison"
                },
                "itemDescription": {
                    "xml:lang": "en",
                    "type": "literal",
                    "value": "British astrophysicist"
                }
            },
            {
                "item": {
                    "type": "uri",
                    "value": "http:\/\/www.wikidata.org\/entity\/Q44381986"
                },
                "article": {
                    "type": "uri",
                    "value": "https:\/\/en.wikipedia.org\/wiki\/John_William_Richmond_Shakespeare"
                },
                "itemLabel": {
                    "xml:lang": "en",
                    "type": "literal",
                    "value": "John Shakespeare"
                },
                "itemDescription": {
                    "xml:lang": "en",
                    "type": "literal",
                    "value": "British diplomat, b. 11 June 1930"
                }
            },
            {
                "item": {
                    "type": "uri",
                    "value": "http:\/\/www.wikidata.org\/entity\/Q44382656"
                },
                "article": {
                    "type": "uri",
                    "value": "https:\/\/en.wikipedia.org\/wiki\/Anthony_J._Camp"
                },
                "itemLabel": {
                    "xml:lang": "en",
                    "type": "literal",
                    "value": "Anthony John Camp"
                },
                "itemDescription": {
                    "xml:lang": "en",
                    "type": "literal",
                    "value": "British genealogist"
                }
            },
            {
                "item": {
                    "type": "uri",
                    "value": "http:\/\/www.wikidata.org\/entity\/Q44399351"
                },
                "article": {
                    "type": "uri",
                    "value": "https:\/\/en.wikipedia.org\/wiki\/Tony_Garrett"
                },
                "itemLabel": {
                    "xml:lang": "en",
                    "type": "literal",
                    "value": "Tony Garrett"
                },
                "itemDescription": {
                    "xml:lang": "en",
                    "type": "literal",
                    "value": "British businessman (1918-2017)"
                }
            },
            {
                "item": {
                    "type": "uri",
                    "value": "http:\/\/www.wikidata.org\/entity\/Q44408535"
                },
                "article": {
                    "type": "uri",
                    "value": "https:\/\/en.wikipedia.org\/wiki\/Duncan_Forbes_(historian)"
                },
                "itemLabel": {
                    "xml:lang": "en",
                    "type": "literal",
                    "value": "Duncan Forbes"
                },
                "itemDescription": {
                    "xml:lang": "en",
                    "type": "literal",
                    "value": "(1922-1994), historian and fellow of Clare College, Cambridge"
                }
            },
            {
                "item": {
                    "type": "uri",
                    "value": "http:\/\/www.wikidata.org\/entity\/Q44426030"
                },
                "article": {
                    "type": "uri",
                    "value": "https:\/\/en.wikipedia.org\/wiki\/Mary_Spencer_Watson"
                },
                "itemLabel": {
                    "xml:lang": "en",
                    "type": "literal",
                    "value": "Mary Spencer Watson"
                },
                "itemDescription": {
                    "xml:lang": "en",
                    "type": "literal",
                    "value": "English sculptor, born 1913"
                }
            },
            {
                "item": {
                    "type": "uri",
                    "value": "http:\/\/www.wikidata.org\/entity\/Q44427237"
                },
                "article": {
                    "type": "uri",
                    "value": "https:\/\/en.wikipedia.org\/wiki\/Edward_Horace_Man"
                },
                "itemLabel": {
                    "xml:lang": "en",
                    "type": "literal",
                    "value": "Edward Horace Man"
                },
                "itemDescription": {
                    "xml:lang": "en",
                    "type": "literal",
                    "value": "(1846-1929) Superintendent of Andaman Islands"
                }
            },
            {
                "item": {
                    "type": "uri",
                    "value": "http:\/\/www.wikidata.org\/entity\/Q44462701"
                },
                "article": {
                    "type": "uri",
                    "value": "https:\/\/en.wikipedia.org\/wiki\/Alan_Jamieson"
                },
                "itemLabel": {
                    "xml:lang": "en",
                    "type": "literal",
                    "value": "Alan J. Jamieson"
                },
                "itemDescription": {
                    "xml:lang": "en",
                    "type": "literal",
                    "value": "British ichthyologist"
                }
            },
            {
                "item": {
                    "type": "uri",
                    "value": "http:\/\/www.wikidata.org\/entity\/Q44476143"
                },
                "article": {
                    "type": "uri",
                    "value": "https:\/\/en.wikipedia.org\/wiki\/John_Jackson_(athlete)"
                },
                "itemLabel": {
                    "xml:lang": "en",
                    "type": "literal",
                    "value": "John Jackson"
                },
                "itemDescription": {
                    "xml:lang": "en",
                    "type": "literal",
                    "value": "British steeplechaser"
                }
            },
            {
                "item": {
                    "type": "uri",
                    "value": "http:\/\/www.wikidata.org\/entity\/Q44476151"
                },
                "article": {
                    "type": "uri",
                    "value": "https:\/\/en.wikipedia.org\/wiki\/Dennis_Coates"
                },
                "itemLabel": {
                    "xml:lang": "en",
                    "type": "literal",
                    "value": "Dennis Coates"
                },
                "itemDescription": {
                    "xml:lang": "en",
                    "type": "literal",
                    "value": "British athlete"
                }
            },
            {
                "item": {
                    "type": "uri",
                    "value": "http:\/\/www.wikidata.org\/entity\/Q44476163"
                },
                "article": {
                    "type": "uri",
                    "value": "https:\/\/en.wikipedia.org\/wiki\/Bill_Brown_(racewalker)"
                },
                "itemLabel": {
                    "xml:lang": "en",
                    "type": "literal",
                    "value": "Bill Brown"
                },
                "itemDescription": {
                    "xml:lang": "en",
                    "type": "literal",
                    "value": "racewalker (1878-1980)"
                }
            },
            {
                "item": {
                    "type": "uri",
                    "value": "http:\/\/www.wikidata.org\/entity\/Q44476173"
                },
                "article": {
                    "type": "uri",
                    "value": "https:\/\/en.wikipedia.org\/wiki\/Ralph_Harrison_(athlete)"
                },
                "itemLabel": {
                    "xml:lang": "en",
                    "type": "literal",
                    "value": "Ralph Harrison"
                },
                "itemDescription": {
                    "xml:lang": "en",
                    "type": "literal",
                    "value": "British racewalker"
                }
            },
            {
                "item": {
                    "type": "uri",
                    "value": "http:\/\/www.wikidata.org\/entity\/Q44476186"
                },
                "article": {
                    "type": "uri",
                    "value": "https:\/\/en.wikipedia.org\/wiki\/John_Butler_(athlete)"
                },
                "itemLabel": {
                    "xml:lang": "en",
                    "type": "literal",
                    "value": "John Butler"
                },
                "itemDescription": {
                    "xml:lang": "en",
                    "type": "literal",
                    "value": "British racewalker and competitor in the 1908 Summer Olympics"
                }
            },
            {
                "item": {
                    "type": "uri",
                    "value": "http:\/\/www.wikidata.org\/entity\/Q44476200"
                },
                "article": {
                    "type": "uri",
                    "value": "https:\/\/en.wikipedia.org\/wiki\/Bruce_Richardson_(Royal_Navy_officer)"
                },
                "itemLabel": {
                    "xml:lang": "en",
                    "type": "literal",
                    "value": "Bruce Richardson"
                }
            },
            {
                "item": {
                    "type": "uri",
                    "value": "http:\/\/www.wikidata.org\/entity\/Q44476218"
                },
                "article": {
                    "type": "uri",
                    "value": "https:\/\/en.wikipedia.org\/wiki\/Eric_Hall_(athlete)"
                },
                "itemLabel": {
                    "xml:lang": "en",
                    "type": "literal",
                    "value": "Eric Hall"
                },
                "itemDescription": {
                    "xml:lang": "en",
                    "type": "literal",
                    "value": "British athletics competitor"
                }
            },
            {
                "item": {
                    "type": "uri",
                    "value": "http:\/\/www.wikidata.org\/entity\/Q44476230"
                },
                "article": {
                    "type": "uri",
                    "value": "https:\/\/en.wikipedia.org\/wiki\/Arthur_Jones_(racewalker)"
                },
                "itemLabel": {
                    "xml:lang": "en",
                    "type": "literal",
                    "value": "Arthur Jones"
                },
                "itemDescription": {
                    "xml:lang": "en",
                    "type": "literal",
                    "value": "British Olympic athlete"
                }
            },
            {
                "item": {
                    "type": "uri",
                    "value": "http:\/\/www.wikidata.org\/entity\/Q44476241"
                },
                "article": {
                    "type": "uri",
                    "value": "https:\/\/en.wikipedia.org\/wiki\/John_Webb_(athlete)"
                },
                "itemLabel": {
                    "xml:lang": "en",
                    "type": "literal",
                    "value": "John Webb"
                },
                "itemDescription": {
                    "xml:lang": "en",
                    "type": "literal",
                    "value": "British Olympic athlete"
                }
            },
            {
                "item": {
                    "type": "uri",
                    "value": "http:\/\/www.wikidata.org\/entity\/Q44476250"
                },
                "article": {
                    "type": "uri",
                    "value": "https:\/\/en.wikipedia.org\/wiki\/Bob_Hughes_(athlete)"
                },
                "itemLabel": {
                    "xml:lang": "en",
                    "type": "literal",
                    "value": "Bob Hughes"
                },
                "itemDescription": {
                    "xml:lang": "en",
                    "type": "literal",
                    "value": "British Olympic athlete"
                }
            },
            {
                "item": {
                    "type": "uri",
                    "value": "http:\/\/www.wikidata.org\/entity\/Q44480460"
                },
                "article": {
                    "type": "uri",
                    "value": "https:\/\/en.wikipedia.org\/wiki\/Tara-Jane_Stanley"
                },
                "itemLabel": {
                    "xml:lang": "en",
                    "type": "literal",
                    "value": "Tara-Jane Stanley"
                },
                "itemDescription": {
                    "xml:lang": "en",
                    "type": "literal",
                    "value": "English rugby league player"
                }
            },
            {
                "item": {
                    "type": "uri",
                    "value": "http:\/\/www.wikidata.org\/entity\/Q44481886"
                },
                "article": {
                    "type": "uri",
                    "value": "https:\/\/en.wikipedia.org\/wiki\/Max_Stedman"
                },
                "itemLabel": {
                    "xml:lang": "en",
                    "type": "literal",
                    "value": "Max Stedman"
                },
                "itemDescription": {
                    "xml:lang": "en",
                    "type": "literal",
                    "value": "British cyclist"
                }
            },
            {
                "item": {
                    "type": "uri",
                    "value": "http:\/\/www.wikidata.org\/entity\/Q44490509"
                },
                "article": {
                    "type": "uri",
                    "value": "https:\/\/en.wikipedia.org\/wiki\/Catherine_Smaill"
                },
                "itemLabel": {
                    "xml:lang": "en",
                    "type": "literal",
                    "value": "Catherine Smaill"
                },
                "itemDescription": {
                    "xml:lang": "en",
                    "type": "literal",
                    "value": "cricketer (born 1991)"
                }
            },
            {
                "item": {
                    "type": "uri",
                    "value": "http:\/\/www.wikidata.org\/entity\/Q44492446"
                },
                "itemLabel": {
                    "xml:lang": "en",
                    "type": "literal",
                    "value": "Lady Charlotte Curzon"
                },
                "itemDescription": {
                    "xml:lang": "en",
                    "type": "literal",
                    "value": "born 1948; daughter of Edward Curzon, 6th Earl Howe, and Grace Wakeling"
                }
            },
            {
                "item": {
                    "type": "uri",
                    "value": "http:\/\/www.wikidata.org\/entity\/Q44493121"
                },
                "itemLabel": {
                    "xml:lang": "en",
                    "type": "literal",
                    "value": "Pat Heslop-Harrison"
                },
                "itemDescription": {
                    "xml:lang": "en",
                    "type": "literal",
                    "value": "British biologist"
                }
            },
            {
                "item": {
                    "type": "uri",
                    "value": "http:\/\/www.wikidata.org\/entity\/Q44500477"
                },
                "article": {
                    "type": "uri",
                    "value": "https:\/\/en.wikipedia.org\/wiki\/Martin_Rush"
                },
                "itemLabel": {
                    "xml:lang": "en",
                    "type": "literal",
                    "value": "Martin Rush"
                },
                "itemDescription": {
                    "xml:lang": "en",
                    "type": "literal",
                    "value": "British athlete"
                }
            },
            {
                "item": {
                    "type": "uri",
                    "value": "http:\/\/www.wikidata.org\/entity\/Q44522629"
                },
                "article": {
                    "type": "uri",
                    "value": "https:\/\/en.wikipedia.org\/wiki\/Thomas_Hele_(academic)"
                },
                "itemLabel": {
                    "xml:lang": "en",
                    "type": "literal",
                    "value": "Thomas Hele"
                },
                "itemDescription": {
                    "xml:lang": "en",
                    "type": "literal",
                    "value": "Vice-Chancellor of the University of Cambridge (1881-1953)"
                }
            },
            {
                "item": {
                    "type": "uri",
                    "value": "http:\/\/www.wikidata.org\/entity\/Q44524670"
                },
                "article": {
                    "type": "uri",
                    "value": "https:\/\/en.wikipedia.org\/wiki\/Gay_Kindersley"
                },
                "itemLabel": {
                    "xml:lang": "en",
                    "type": "literal",
                    "value": "Gay Kindersley"
                },
                "itemDescription": {
                    "xml:lang": "en",
                    "type": "literal",
                    "value": "(1930-2011)"
                }
            },
            {
                "item": {
                    "type": "uri",
                    "value": "http:\/\/www.wikidata.org\/entity\/Q44527017"
                },
                "article": {
                    "type": "uri",
                    "value": "https:\/\/en.wikipedia.org\/wiki\/Philip_Callow"
                },
                "itemLabel": {
                    "xml:lang": "en",
                    "type": "literal",
                    "value": "Philip Callow"
                },
                "itemDescription": {
                    "xml:lang": "en",
                    "type": "literal",
                    "value": "(1924-2007), novelist"
                }
            },
            {
                "item": {
                    "type": "uri",
                    "value": "http:\/\/www.wikidata.org\/entity\/Q44530849"
                },
                "article": {
                    "type": "uri",
                    "value": "https:\/\/en.wikipedia.org\/wiki\/Virginia_Surtees"
                },
                "itemLabel": {
                    "xml:lang": "en",
                    "type": "literal",
                    "value": "Virginia Surtees"
                },
                "itemDescription": {
                    "xml:lang": "en",
                    "type": "literal",
                    "value": "English art historian and author"
                }
            },
            {
                "item": {
                    "type": "uri",
                    "value": "http:\/\/www.wikidata.org\/entity\/Q44537064"
                },
                "article": {
                    "type": "uri",
                    "value": "https:\/\/en.wikipedia.org\/wiki\/Gene_Carney"
                },
                "itemLabel": {
                    "xml:lang": "en",
                    "type": "literal",
                    "value": "Gene Carney"
                },
                "itemDescription": {
                    "xml:lang": "en",
                    "type": "literal",
                    "value": "association football player (1895-1952)"
                }
            },
            {
                "item": {
                    "type": "uri",
                    "value": "http:\/\/www.wikidata.org\/entity\/Q44538481"
                },
                "article": {
                    "type": "uri",
                    "value": "https:\/\/en.wikipedia.org\/wiki\/Thomas_Stewart_Patterson"
                },
                "itemLabel": {
                    "xml:lang": "en",
                    "type": "literal",
                    "value": "Thomas Stewart Patterson"
                },
                "itemDescription": {
                    "xml:lang": "en",
                    "type": "literal",
                    "value": "this article is about a Scottish organic chemist"
                }
            },
            {
                "item": {
                    "type": "uri",
                    "value": "http:\/\/www.wikidata.org\/entity\/Q44540516"
                },
                "article": {
                    "type": "uri",
                    "value": "https:\/\/en.wikipedia.org\/wiki\/Oswald_Staniforth"
                },
                "itemLabel": {
                    "xml:lang": "en",
                    "type": "literal",
                    "value": "Oswald Staniforth"
                },
                "itemDescription": {
                    "xml:lang": "en",
                    "type": "literal",
                    "value": "Franciscan monk"
                }
            },
            {
                "item": {
                    "type": "uri",
                    "value": "http:\/\/www.wikidata.org\/entity\/Q44544812"
                },
                "article": {
                    "type": "uri",
                    "value": "https:\/\/en.wikipedia.org\/wiki\/Curtis_Yorke"
                },
                "itemLabel": {
                    "xml:lang": "en",
                    "type": "literal",
                    "value": "Curtis Yorke"
                },
                "itemDescription": {
                    "xml:lang": "en",
                    "type": "literal",
                    "value": "Scottish writer"
                }
            },
            {
                "item": {
                    "type": "uri",
                    "value": "http:\/\/www.wikidata.org\/entity\/Q44610004"
                },
                "itemLabel": {
                    "xml:lang": "en",
                    "type": "literal",
                    "value": "George C. Boon"
                },
                "itemDescription": {
                    "xml:lang": "en",
                    "type": "literal",
                    "value": "archaeologist and museum curator"
                }
            },
            {
                "item": {
                    "type": "uri",
                    "value": "http:\/\/www.wikidata.org\/entity\/Q44613326"
                },
                "article": {
                    "type": "uri",
                    "value": "https:\/\/en.wikipedia.org\/wiki\/Elderbrook"
                },
                "itemLabel": {
                    "xml:lang": "en",
                    "type": "literal",
                    "value": "Elderbrook"
                },
                "itemDescription": {
                    "xml:lang": "en",
                    "type": "literal",
                    "value": "British electronic musician"
                }
            },
            {
                "item": {
                    "type": "uri",
                    "value": "http:\/\/www.wikidata.org\/entity\/Q44625831"
                },
                "article": {
                    "type": "uri",
                    "value": "https:\/\/en.wikipedia.org\/wiki\/Henry_Cieman"
                },
                "itemLabel": {
                    "xml:lang": "en",
                    "type": "literal",
                    "value": "Henry Cieman"
                },
                "itemDescription": {
                    "xml:lang": "en",
                    "type": "literal",
                    "value": "Canadian athlete"
                }
            },
            {
                "item": {
                    "type": "uri",
                    "value": "http:\/\/www.wikidata.org\/entity\/Q44627566"
                },
                "article": {
                    "type": "uri",
                    "value": "https:\/\/en.wikipedia.org\/wiki\/Michael_Cumming"
                },
                "itemLabel": {
                    "xml:lang": "en",
                    "type": "literal",
                    "value": "Michael Cumming"
                },
                "itemDescription": {
                    "xml:lang": "en",
                    "type": "literal",
                    "value": "British director and filmmaker"
                }
            },
            {
                "item": {
                    "type": "uri",
                    "value": "http:\/\/www.wikidata.org\/entity\/Q44629488"
                },
                "article": {
                    "type": "uri",
                    "value": "https:\/\/en.wikipedia.org\/wiki\/William_Balthazar_Rose"
                },
                "itemLabel": {
                    "xml:lang": "en",
                    "type": "literal",
                    "value": "William Balthazar Rose"
                },
                "itemDescription": {
                    "xml:lang": "en",
                    "type": "literal",
                    "value": "British painter"
                }
            },
            {
                "item": {
                    "type": "uri",
                    "value": "http:\/\/www.wikidata.org\/entity\/Q44635337"
                },
                "article": {
                    "type": "uri",
                    "value": "https:\/\/en.wikipedia.org\/wiki\/Clayton_Howard"
                },
                "itemLabel": {
                    "xml:lang": "en",
                    "type": "literal",
                    "value": "Clayton Howard"
                },
                "itemDescription": {
                    "xml:lang": "en",
                    "type": "literal",
                    "value": "British make-up artist"
                }
            },
            {
                "item": {
                    "type": "uri",
                    "value": "http:\/\/www.wikidata.org\/entity\/Q44642475"
                },
                "article": {
                    "type": "uri",
                    "value": "https:\/\/en.wikipedia.org\/wiki\/Jonathan_Pentreath"
                },
                "itemLabel": {
                    "xml:lang": "en",
                    "type": "literal",
                    "value": "Jonathan Pentreath"
                },
                "itemDescription": {
                    "xml:lang": "en",
                    "type": "literal",
                    "value": "Royal Navy rear-admiral"
                }
            }
        ]
    }
}