{"wiki_id": "http://www.wikidata.org/entity/Q11225096", "itemLabel": "George Edward Cotterill", "itemDescription": "English cricketer (1839-1913)", "wikipedia_url": "https://en.wikipedia.org/wiki/George_Edward_Cotterill", "wikipedia_page": {"main": "George Edward Cotterill (28 July 1839 \u2013 2 June 1913) was an English cricketer active from 1858 to 1874 who played for Cambridge Town Club (aka Cambridgeshire), Sussex and Cambridge University. He was born at Weilghery Hills, Madras and died in Cambridge. He appeared in 18 first-class matches as a righthanded batsman and occasional wicketkeeper who bowled underarm. He scored 447 runs with a highest score of 55 and held five catches with two stumpings. He took 14 wickets with a best analysis of five for 23.Cotterill was educated at Brighton College and St John's College, Cambridge. He was made a deacon in  Grahamstown, South Africa in 1863 and ordained as a priest in 1864 by his father, the Rt Revd Henry Cotterill, the bishop of Grahamstown at the time.His brother Joseph Cotterill played 37 first-class matches, mainly for Sussex, from 1870 to 1888. Cotterill's son was George Huth Cotterill, who also played for Cambridge University and Sussex.\nCotterill had an academic career and was successively Headmaster of St. Andrew's College, Grahamstown (1862\u201365); Assistant Master at Brighton College (1865\u201381); Headmaster of St Bernard's, Woking (1881\u201387); Headmaster of Weybridge School (1887\u201395); and Rector at Idlicote, Warwickshire (1896-1911).", "link_mentions": {}}}