{"wiki_id": "http://www.wikidata.org/entity/Q1542688", "itemLabel": "Jack Maxsted", "itemDescription": "art director (1916-2001)", "wikipedia_url": "https://en.wikipedia.org/wiki/Jack_Maxsted", "wikipedia_page": {"main": "Albert John Maxsted (30 April 1916 \u2013 September 2001) was an English art director. He won an Academy Award in the category Best Art Direction for the film Nicholas and Alexandra.", "link_mentions": [{"page": "Academy Award for Best Production Design", "response": ["| John Box, Ernest Archer, Jack Maxsted and Gil Parrondo"]}, {"page": "Nicholas and Alexandra", "response": ["* John Box, Ernest Archer, Jack Maxsted, Gil Parrondo, Vernon Dixon won Best Art Direction."]}, {"page": "44th Academy Awards", "response": ["*Nicholas and Alexandra\u00a0\u2013 Art Direction: Ernest Archer, John Box, Jack Maxsted and Gil Parrondo; Set Decoration: Vernon Dixon"]}]}}