{"wiki_id": "http://www.wikidata.org/entity/Q16065952", "itemLabel": "John Walpole", "itemDescription": "British politician", "wikipedia_url": "https://en.wikipedia.org/wiki/John_Walpole", "wikipedia_page": {"main": "Colonel John Walpole (17 November 1787 \u2013 10 December 1859) was a soldier and diplomat, a younger son of Horatio Walpole, 2nd Earl of Orford.\nHe served with the Guards during the Peninsular War, and was wounded at the Siege of Burgos.  He was Member of Parliament for King's Lynn from 1822 to 1831. Walpole served as private secretary to Lord Palmerston from November 1830 to August 1833, when he was appointed British Consul-General and Plentipotentiary at Santiago in Chile. Walpole was promoted to Charg\u00e9 d'affaires in May 1841, and retired in March 1849.\n\n", "link_mentions": {}}}