{"wiki_id": "http://www.wikidata.org/entity/Q16929716", "itemLabel": "William McGinnigle", "itemDescription": "Scottish footballer (1892-1947)", "wikipedia_url": "https://en.wikipedia.org/wiki/William_McGinnigle", "wikipedia_page": {"main": "William George McGinnigle (5 June 1892 \u2013 11 Oct 1947) was a Scottish footballer who played as a right back for Cambuslang Rangers, Hibernian, Celtic and Coleraine.He made 333 appearances for Hibs in the Scottish Football League and Scottish Cup including two finals of the knockout competition (1923 and 1924, both ending in defeat). In contrast, he played in only one league fixture for Celtic on an emergency loan due to wartime circumstances in 1918, which they won on the way to winning the championship by a single point.\nHe was selected once for the Scottish Football League XI in 1924 and took part in the Home Scots v Anglo-Scots trial match a year earlier, but never received a full international cap.\nMcGinnigle served in the British Army Argyll & Sutherland Highlanders during the First World War and he was awarded the 1914-15 Star, British War Medal and the Victory Medal.", "link_mentions": [{"page": "1923\u201324 Scottish Cup", "response": ["|RB |||| William McGinnigle"]}, {"page": "1922\u201323 Scottish Cup", "response": ["|RB |||| William McGinnigle"]}, {"page": "McGinnigle, William", "response": ["#redirectWilliam McGinnigle"]}]}}