{"wiki_id": "http://www.wikidata.org/entity/Q17198877", "itemLabel": "Stanley Brown", "itemDescription": "British cricketer (1877-1952)", "wikipedia_url": "https://en.wikipedia.org/wiki/Stanley_Brown_(cricketer,_born_1877)", "wikipedia_page": {"main": "William Stanley Alston Brown, known as Stanley Brown (23 May 1877 \u2013 12 September 1952) was an English cricketer who played for Gloucestershire as a right-handed batsman and left-arm slow bowler between 1896 and 1919. He made over 160 appearances in first-class cricket, scoring 4,820 runs and taking 195 wickets. He was born in Clifton and died in Kingsdown, both areas of Bristol.\n\n", "link_mentions": [{"page": "Stan Brown", "response": ["* Stanley Brown (cricketer, born 1877) (1877\u20131952), English cricketer", "* Stanley Brown (cricketer, born 1907) (1907\u20131978), English cricketer", "* Stanley Brown (actor), who appeared in the 1941 film Harvard, Here I Come", "* Stanley Brown (engineer) (1910\u20131997), English mechanical and electrical engineer", "* Stanley Brown, a character in the 1950 film State Penitentiary"]}, {"page": "List of Gloucestershire County Cricket Club players", "response": ["* Stanley Brown (1896\u20131919) : W. S. A. Brown"]}, {"page": "List of Gentlemen cricketers (1841\u20131962)", "response": ["* Stanley Brown (1905)"]}]}}