{"wiki_id": "http://www.wikidata.org/entity/Q20876756", "itemLabel": "Francis Musson", "itemDescription": "cricketer (1894-1962)", "wikipedia_url": "https://en.wikipedia.org/wiki/Francis_Musson", "wikipedia_page": {"main": "Francis William Musson  (31 May 1894 \u2013 2 January 1962) was an English cricketer active from 1914 to 1927 who played for Lancashire. He was born in Clitheroe and died in Chatham. He appeared in 19 first-class matches as a righthanded batsman and wicketkeeper. He scored 539 runs with a highest score of 75 and held 13 catches with four stumpings.", "link_mentions": {}}}