{"wiki_id": "http://www.wikidata.org/entity/Q24006212", "itemLabel": "Anthony Rogers", "itemDescription": "British motorcycle racer", "wikipedia_url": "https://en.wikipedia.org/wiki/Anthony_Rogers_(motorcyclist)", "wikipedia_page": {"main": "Anthony Derek Rogers (born 3 April 1990 in Norwich, Norfolk) is a Grand Prix motorcycle racer from United Kingdom.", "link_mentions": [{"page": "Anthony Rogers", "response": ["Anthony Rogers may refer to:", "*Anthony Rogers (actor), English actor", "*Anthony Rogers (motorcyclist) (born 1990), British motorcycle racer", "*Buck Rogers, a fictional character originally called Anthony Rogers"]}, {"page": "Anthony Rogers (motorcycle racer)", "response": ["#REDIRECT Anthony Rogers (motorcyclist)"]}]}}