{"wiki_id": "http://www.wikidata.org/entity/Q26328883", "itemLabel": "Chris Bennett", "itemDescription": "British athletics competitor", "wikipedia_url": "https://en.wikipedia.org/wiki/Chris_Bennett_(hammer_thrower)", "wikipedia_page": {"main": "Chris Bennett (born 17 December 1989 in Aberdeen, Scotland) is a British hammer thrower. He competed at the 2016 Summer Olympics in the men's hammer throw event. He represented Scotland at the 2014 Commonwealth Games.", "link_mentions": [{"page": "Chris Bennett", "response": ["Chris Bennett may refer to:", "* Chris Bennett (admiral) (born 1937), South African admiral and author", "* Chris Bennett (musician) (born 1948), American singer, dancer and composer", "* Chris Bennett (soccer) (born 1952), former Canadian international and NASL soccer player", "* Chris Bennett (hammer thrower) (born 1989), British hammer thrower", "* Chris Bennett (hurler), Irish hurler", "* Chris Bennett (1953\u20132014), British-born American Egyptologist who founded The Egyptian Royal Genealogy Project"]}, {"page": "2015 British Athletics Championships", "response": ["|Chris Bennett ||72.62 m"]}, {"page": "Chris Bennett (athlete)", "response": ["#REDIRECT Chris Bennett (hammer thrower)"]}, {"page": "List of British champions in hammer throw", "response": ["|Chris Bennett"]}, {"page": "2020 British Athletics Championships", "response": ["|Chris BennettShaftesbury || 68.84\t\t\t\t\t\t"]}, {"page": "2021 European Throwing Cup", "response": ["| bgcolor=DCE5E5| Chris Bennett || 75.36"]}, {"page": "2021 European Athletics Team Championships Super League", "response": ["| 4 || align=left|Chris Bennett || align=left| || 68.75 || 72.62 || 72.73 || 74.09 || 74.09 ||   || 4"]}, {"page": "2021 British Athletics Championships", "response": ["|Chris Bennett || 73.53m"]}]}}