{"wiki_id": "http://www.wikidata.org/entity/Q39161942", "itemLabel": "Kavan Cotter", "itemDescription": "association football player (born 1999)", "wikipedia_url": "https://en.wikipedia.org/wiki/Kavan_Cotter", "wikipedia_page": {"main": "Kavan John Cotter (born 3 May 1999) is an English semi-professional footballer who plays as a midfielder for National League club Wealdstone.", "link_mentions": [{"page": "2016\u201317 Luton Town F.C. season", "response": ["!scope=row|Kavan Cotter"]}, {"page": "2017\u201318 Luton Town F.C. season", "response": ["Luton began the season at home to Yeovil Town and won the match 8\u20132, the club's biggest Football League victory since a 6\u20130 win over Crewe Alexandra in December 1996. Otis Khan gave the away team the lead in the seventh minute with a free kick from 22 yards, before Olly Lee equalised five minutes later with a volley from Isaac Vassell's cross. James Collins put Luton in front on 19 minutes when he chipped the ball over goalkeeper Artur Krysiak and into the net, before Alan McCormack scored with a volley from 25 yards five minutes later to make the score 3\u20131. Vassell then scored twice in two minutes to give Luton a 5\u20131 lead, before Marek \u0160t\u011bch saved a penalty from Khan to ensure the score remained the same going into half-time. Collins scored twice in eight minutes after half-time to complete his hat-trick, before Fran\u00e7ois Zoko scored a consolation goal for Yeovil a minute later with a header from Ryan Dickson's cross, and Elliot Lee scored Luton's eighth goal in the ninth minute of stoppage time. Transfer-listed midfielder Jonathan Smith had his contract with Luton terminated by mutual consent, allowing him to join Stevenage, while forward Harry Cornick was signed from AFC Bournemouth on a two-year contract, with the option of a one-year extension, for an undisclosed fee. Luton were knocked out of the EFL Cup in the first round after being beaten 2\u20130 at home to Championship club Ipswich Town, who scored in each half through David McGoldrick. Frankie Musonda signed a new contract with Luton, which contracted him to the club until the summer of 2019, and Kavan Cotter joined Southern League Premier Division club Hitchin Town on a one-month youth loan. Luton suffered their first league defeat of the season after losing 1\u20130 to Barnet, who scored in second-half stoppage time through Jack Taylor with a 25-yard curling shot. Vassell joined Championship club Birmingham City for an undisclosed fee.", "|Kavan Cotter", "|Kavan Cotter", "|Kavan Cotter", "|Kavan Cotter", "|Kavan Cotter", "!scope=row|Kavan Cotter"]}, {"page": "2018\u201319 Luton Town F.C. season", "response": ["|Kavan Cotter"]}]}}