{"wiki_id": "http://www.wikidata.org/entity/Q5537026", "itemLabel": "George Blackburn", "itemDescription": "English footballer and manager (1899-1957)", "wikipedia_url": "https://en.wikipedia.org/wiki/George_Blackburn_(footballer,_born_1899)", "wikipedia_page": {"main": "George Fredrick Blackburn (3 August 1899 \u2013 7 March 1957) was a footballer in the early years of professional football in England. A left-half, made over 250 appearances in the Football League during his career and won one cap for England in May 1924.", "link_mentions": {}}}