{"wiki_id": "http://www.wikidata.org/entity/Q5549582", "itemLabel": "Gerald Sly", "itemDescription": "cricketer (born 1932)", "wikipedia_url": "https://en.wikipedia.org/wiki/Gerald_Sly", "wikipedia_page": {"main": "Gerald Brian Sly (born 21 October 1932) is a former English cricketer.  Sly was a right-handed batsman who bowled right-arm fast-medium.  He was born at Ealing, Middlesex.\nSly made a single first-class appearance for Sussex against Oxford University at the County Ground, Hove in 1953.  He didn't bat in this match, but did take the wicket of Colin Cowdrey in Oxford University's first-innings.  The match ended in a draw.  This was his only major appearance for Sussex.", "link_mentions": []}}