{"wiki_id": "http://www.wikidata.org/entity/Q5584808", "itemLabel": "Gordon Archbold Slater", "itemDescription": "British musician", "wikipedia_url": "https://en.wikipedia.org/wiki/Gordon_Archbold_Slater", "wikipedia_page": {"main": "Gordon Archbold Slater  D.Mus. FRCO (1896\u20131979) was an English cathedral organist, who served in Leicester Cathedral and Lincoln Cathedral.He was a composer of organ, piano and choral music.", "link_mentions": [{"page": "St Botolph's Church, Boston", "response": ["* Gordon Archbold Slater 1919 - 1927 (later organist of Lincoln Cathedral)"]}, {"page": "Leicester Cathedral", "response": ["*Gordon Archbold Slater 1927\u20131931 (subsequently organist at Lincoln Cathedral 1931\u20131966)"]}, {"page": "Dennis Townhill", "response": ["Born in Lincoln, he was educated at Lincoln School and studied under Dr Gordon Archbold Slater at Lincoln Cathedral."]}, {"page": "Slater (surname)", "response": ["*Gordon Archbold Slater (1896\u20131979), English cathedral organist"]}, {"page": "List of musicians at English cathedrals", "response": ["*Gordon Archbold Slater 1927\u20131931 (subsequently organist at Lincoln Cathedral 1931\u20131966)", "* 1930 Gordon Archbold Slater"]}, {"page": "Gordon Slater", "response": ["* Gordon Archbold Slater (1896\u20131979), English cathedral organist"]}]}}