{"wiki_id": "http://www.wikidata.org/entity/Q6227575", "itemLabel": "John Creemer Clarke", "itemDescription": "British politician", "wikipedia_url": "https://en.wikipedia.org/wiki/John_Creemer_Clarke", "wikipedia_page": {"main": "John Creemer Clarke (1821 \u2013 11 February 1895) was an English merchant and manufacturer and a  Liberal politician who sat in the House of Commons from 1874 to 1885.", "link_mentions": [{"page": "Abingdon-on-Thames", "response": ["*John Creemer Clarke (1821\u201395), clothing manufacturer (Hyde and Clarke), JP, MP, benefactor"]}, {"page": "John Clarke", "response": ["*John Creemer Clarke (1821\u20131895), British Member of Parliament"]}, {"page": "Abingdon (UK Parliament constituency)", "response": ["|John Creemer Clarke || Liberal"]}, {"page": "List of MPs elected in the 1880 United Kingdom general election", "response": ["| John Creemer Clarke"]}, {"page": "List of MPs elected in the 1874 United Kingdom general election", "response": ["| John Creemer Clarke"]}]}}