{"wiki_id": "http://www.wikidata.org/entity/Q6439799", "itemLabel": "Krystle Robba", "itemDescription": "Gibraltarian model", "wikipedia_url": "https://en.wikipedia.org/wiki/Krystle_Robba", "wikipedia_page": {"main": "Miss Gibraltar is a national beauty pageant in Gibraltar.", "link_mentions": [{"page": "Kaiane Aldorino", "response": ["On 27 June 2009, Aldorino was crowned Miss Gibraltar 2009, succeeding Krystle Robba at the Alameda Open Air Theatre."]}, {"page": "Miss Gibraltar", "response": ["| Krystle Robba "]}, {"page": "History of the Genoese in Gibraltar", "response": ["* Krystle Robba (Miss Gibraltar 2008)"]}]}}