{"wiki_id": "http://www.wikidata.org/entity/Q6504865", "itemLabel": "Lawrie Tierney", "itemDescription": "Scottish footballer (1959-2011)", "wikipedia_url": "https://en.wikipedia.org/wiki/Lawrie_Tierney", "wikipedia_page": {"main": "Lawrence James William \"Lawrie\" Tierney (4 April 1959 \u2013 6 December 2011) was a Scottish footballer who played as a midfielder. Born in Leith, Tierney started his professional career at Heart of Midlothian in 1976, making 49 league appearances for the club before being released in February 1980. He then had brief spells at Hibernian and Wigan Athletic before moving to the United States, where he played in the Major Indoor Soccer League for Phoenix Inferno, Golden Bay Earthquakes and Tacoma Stars.", "link_mentions": [{"page": "Tierney", "response": ["* Lawrie Tierney (1959\u20132011), Scottish professional football (soccer) player"]}, {"page": "Edinburgh derby", "response": ["|Lawrie Tierney"]}, {"page": "2011 in association football", "response": ["* 6 December \u2013 Lawrie Tierney, Scottish footballer (52)"]}, {"page": "2011\u201312 in Scottish football", "response": ["* 6 December: Lawrie Tierney, 52, Hearts and Hibs midfielder."]}, {"page": "Deaths in December 2011", "response": ["*Lawrie Tierney, 52, Scottish footballer."]}]}}